mcp_chaoshen_100_01/__init__.py
mcp_chaoshen_100_01-0.1.0.dist-info/METADATA
mcp_chaoshen_100_01-0.1.0.dist-info/WHEEL
mcp_chaoshen_100_01-0.1.0.dist-info/entry_points.txt
mcp_chaoshen_100_01-0.1.0.dist-info/RECORD
