Metadata-Version: 2.4
Name: mcp-chaoshen-100-01
Version: 0.1.0
Summary: Add your description here
Author-email: liuchao11 <liuchao11@staff.weibo.com>
Requires-Python: >=3.13
Requires-Dist: mcp[cli]>=1.10.1
